<workout>
	<workoutSample>
		<source>
			<bundleID>com.apple.health.FFE97E1E-1E63-4F60-B359-E74265E33CB7</bundleID>
			<productType>Watch6,6</productType>
			<source>Kronos</source>
			<version>11.1</version>
		</source>
		<sampleType>
			<identifier>HKWorkoutTypeIdentifier</identifier>
		</sampleType>
		<energyBurned>
			<value>47.406</value>
			<unit>kcal</unit>
		</energyBurned>
		<startDate>1734332420.764</startDate>
		<endDate>1734333131.95</endDate>
		<duration>711.186</duration>
		<activityType>57</activityType>
		<metadata>
			<HKIndoorWorkout>0</HKIndoorWorkout>
			<HKTimeZone>America/Los_Angeles</HKTimeZone>
			<HKAverageMETs>
				<value>3.175</value>
				<unit>kcal/hr·kg</unit>
			</HKAverageMETs>
		</metadata>
	</workoutSample>
	<workoutSample>
		<source>
			<bundleID>com.apple.health.FFE97E1E-1E63-4F60-B359-E74265E33CB7</bundleID>
			<productType>Watch6,6</productType>
			<source>Kronos</source>
			<version>11.2</version>
		</source>
		<sampleType>
			<identifier>HKWorkoutTypeIdentifier</identifier>
		</sampleType>
		<energyBurned>
			<value>49.531</value>
			<unit>kcal</unit>
		</energyBurned>
		<startDate>1734381304.406</startDate>
		<endDate>1734382048.71</endDate>
		<duration>744.304</duration>
		<activityType>57</activityType>
		<metadata>
			<HKIndoorWorkout>0</HKIndoorWorkout>
			<HKTimeZone>America/Los_Angeles</HKTimeZone>
			<HKAverageMETs>
				<value>3.403</value>
				<unit>kcal/hr·kg</unit>
			</HKAverageMETs>
		</metadata>
	</workoutSample>
	<datatype>HKWorkoutTypeIdentifier</datatype>
	<workoutType>57</workoutType>
</workout>
